wivi-graph-lib/__init__.py
wivi-graph-lib/client.py
wivi-graph-lib/configuration.py
wivi-graph-lib/device_connection.py
wivi-graph-lib/device_info.py
wivi-graph-lib/device_status.py
wivi-graph-lib/device_version.py
wivi-graph-lib/dtc.py
wivi-graph-lib/ecu.py
wivi-graph-lib/fail_processing.py
wivi-graph-lib/formula.py
wivi-graph-lib/gps.py
wivi-graph-lib/main.py
wivi-graph-lib/message.py
wivi-graph-lib/network.py
wivi-graph-lib/network_stats.py
wivi-graph-lib/signal.py
wivi-graph-lib/test_configuration.py
wivi-graph-lib/test_device_connection.py
wivi-graph-lib/test_device_version.py
wivi-graph-lib/test_dtc.py
wivi-graph-lib/test_fail_processing.py
wivi-graph-lib/test_gps.py
wivi-graph-lib/test_message.py
wivi-graph-lib/test_network_stats.py
wivi-graph-lib/test_signal.py
wivi-graph-lib/version.py
wivigraphlib/__init__.py
wivigraphlib/client.py
wivigraphlib/configuration.py
wivigraphlib/device_connection.py
wivigraphlib/device_info.py
wivigraphlib/device_status.py
wivigraphlib/device_version.py
wivigraphlib/dtc.py
wivigraphlib/ecu.py
wivigraphlib/fail_processing.py
wivigraphlib/formula.py
wivigraphlib/gps.py
wivigraphlib/main.py
wivigraphlib/message.py
wivigraphlib/network.py
wivigraphlib/network_stats.py
wivigraphlib/signal.py
wivigraphlib/test_configuration.py
wivigraphlib/test_device_connection.py
wivigraphlib/test_device_version.py
wivigraphlib/test_dtc.py
wivigraphlib/test_fail_processing.py
wivigraphlib/test_gps.py
wivigraphlib/test_message.py
wivigraphlib/test_network_stats.py
wivigraphlib/test_signal.py
wivigraphlib/version.py
wivigraphlibfix/__init__.py
wivigraphlibfix/client.py
wivigraphlibfix/configuration.py
wivigraphlibfix/device_connection.py
wivigraphlibfix/device_info.py
wivigraphlibfix/device_status.py
wivigraphlibfix/device_version.py
wivigraphlibfix/dtc.py
wivigraphlibfix/ecu.py
wivigraphlibfix/fail_processing.py
wivigraphlibfix/formula.py
wivigraphlibfix/gps.py
wivigraphlibfix/main.py
wivigraphlibfix/message.py
wivigraphlibfix/network.py
wivigraphlibfix-2.2.6.dist-info/METADATA
wivigraphlibfix-2.2.6.dist-info/WHEEL
wivigraphlibfix-2.2.6.dist-info/top_level.txt
wivigraphlibfix-2.2.6.dist-info/RECORD
